flask_mpesa/__init__.py
flask_mpesa/api/__init__.py
flask_mpesa/api/auth.py
flask_mpesa/api/b2b.py
flask_mpesa/api/b2c.py
flask_mpesa/api/balance.py
flask_mpesa/api/c2b.py
flask_mpesa/api/mpesa_express.py
flask_mpesa/api/reversal.py
flask_mpesa/api/transaction_status.py
flask_mpesa/tests/__init__.py
flask_mpesa/tests/base.py
flask_mpesa/tests/conftest.py
flask_mpesa/tests/data.py
flask_mpesa/tests/test_base.py
Flask_Mpesa-1.2.8.dist-info/LICENSE
Flask_Mpesa-1.2.8.dist-info/METADATA
Flask_Mpesa-1.2.8.dist-info/WHEEL
Flask_Mpesa-1.2.8.dist-info/top_level.txt
Flask_Mpesa-1.2.8.dist-info/RECORD
